asyncping3/__init__.py
asyncping3/__main__.py
asyncping3/command_line.py
asyncping3/enums.py
asyncping3/errors.py
asyncping3-5.1.3.dist-info/licenses/LICENSE
asyncping3-5.1.3.dist-info/METADATA
asyncping3-5.1.3.dist-info/WHEEL
asyncping3-5.1.3.dist-info/entry_points.txt
asyncping3-5.1.3.dist-info/top_level.txt
asyncping3-5.1.3.dist-info/RECORD
