Metadata-Version: 2.4
Name: asyncping3
Version: 5.1.3
Summary: An async-friendly pure python3 version of ICMP ping implementation using raw socket.
Author-email: Matthias Urlichs <matthias@urlichs.de>
License-Expression: MIT
Project-URL: Homepage, https://github.com/M-o-a-T/asyncping3
Project-URL: Changelog, https://github.com/M-o-a-T/asyncping3/blob/master/CHANGELOG.md
Project-URL: Issue Tracker, https://github.com/M-o-a-T/asyncping3/issues
Project-URL: Source Code, https://github.com/M-o-a-T/asyncping3
Keywords: python3,anyio,ping,icmp,socket,tool
Classifier: Development Status :: 5 - Production/Stable
Classifier: Intended Audience :: Developers
Classifier: Intended Audience :: End Users/Desktop
Classifier: Topic :: System :: Networking
Classifier: Programming Language :: Python :: 3
Classifier: Programming Language :: Python :: 3 :: Only
Requires-Python: >=3.9
License-File: LICENSE
Provides-Extra: dev
Requires-Dist: build; extra == "dev"
Requires-Dist: twine; extra == "dev"
Dynamic: license-file
